generate_report/__init__.py
generate_report/chrome_driver.py
generate_report/config.yml
generate_report/db_connect.py
generate_report/get_db.py
generate_report/project_data.yml
generate_report/run.py
generate_report/template.docx
generate_report/test_report.py
generate_report-1.0.0.dist-info/METADATA
generate_report-1.0.0.dist-info/WHEEL
generate_report-1.0.0.dist-info/top_level.txt
generate_report-1.0.0.dist-info/RECORD
