Metadata-Version: 2.1
Name: generate-report
Version: 1.0.0
Summary: 自动生成测试报告工具
Home-page: http://gitlab.py.in:280/fuxiaoxiao/report_origin
Author: FuXiaoXiao
Author-email: fuxiaoxiao@pystandard.com
License: UNKNOWN
Platform: UNKNOWN
